{
  "lyrics": [
    {
      "contents": [
        {
          "c_id": 0,
          "statement": "주 이름 찬양\n풍요의 강물 흐르는\n부요한 땅에 살때에\n주님 찬양해"
        },
        {
          "c_id": 1,
          "statement": "주 이름 찬양\n거치른 광야와 같은\n인생길 걸어 갈때도\n주님 찬양해"
        },
        {
          "c_id": 2,
          "statement": "모든 축복 주신 주님 찬양하리\n어둔날이 다가와도 난 외치리"
        },
        {
          "c_id": 3,
          "statement": "주의 이름을 찬양해\n주의 이름을 \n주의 이름을 찬양해\n영화로운 주 이름 찬양"
        },
        {
          "c_id": 4,
          "statement": "-2절-"
        },
        {
          "c_id": 5,
          "statement": "주이름 찬양\n햇살이 나를 비추고\n만물이 새롭게 될때 \n주님 찬양해"
        },
        {
          "c_id": 6,
          "statement": "주 이름 찬양\n가는길 험할 지라도\n고통이 따를 지라도\n주님 찬양해"
        },
        {
          "c_id": 7,
          "statement": "모든축복 주신 주님\n찬양하리\n어둔 날이 다가와도 \n난외치리"
        },
        {
          "c_id": 8,
          "statement": "주의 이름을 찬양해\n주의 이름을 \n주의 이름을 찬양해\n영화로운 주 이름 찬양 x2"
        },
        {
          "c_id": 9,
          "statement": "-간주-"
        },
        {
          "c_id": 10,
          "statement": "주 이름 찬양\n풍요의 강물 흐르는\n부요한 땅에 살때에\n주님 찬양해"
        },
        {
          "c_id": 11,
          "statement": "주 이름 찬양\n거치른 광야와 같은\n인생길 걸어 갈때도\n주님 찬양해"
        },
        {
          "c_id": 12,
          "statement": "주님은 주시며 주님은 찾으시네\n내 맘에 하는말 주 찬양 합니다. x5"
        },
        {
          "c_id": 13,
          "statement": "주의 이름을 찬양해 \n주의 이름을 \n주의 이름을 찬양해\n영화로운 주 이름 찬양 x2"
        }
      ],
      "title": "주이름 찬양",
      "code": "A",
      "file": "주이름찬양A.jpg",
      "l_id": 1
    },
    {
      "contents": [
        {
          "c_id": 0,
          "statement": "작은 갈대 상자 \n물이 새지 않도록\n역청과 나무 진을 칠하네\n어떤 맘이었을까 \n그녀의 두 눈엔\n눈물이 흐르고 흘러"
        },
        {
          "c_id": 1,
          "statement": "동그란 눈으로 \n엄마를 보고 있는\n아이와 입을 맞추고\n상자를 덮고 강가에 띄우며\n간절히 기도했겠지"
        },
        {
          "c_id": 2,
          "statement": "정처 없이 강물에 흔들 흔들\n흘러 내려가는 그 상자를 보며\n눈을 감아도 보이는 아이와\n눈을 맞추며\n주저 앉아 눈물을 흘렸겠지"
        },
        {
          "c_id": 3,
          "statement": "너의 삶의 참 주인 \n너의 참 부모이신\n하나님 그 손에 \n너의 삶을 맡긴다\n너의 삶의 참 주인 \n너를 이끄시는 주\n하나님 그 손에 \n너의 삶을 드린다"
        },
        {
          "c_id": 4,
          "statement": "어떤 맘이었을까 \n그녀의 두 눈엔\n눈물이 흐르고 흘러\n정처 없이 강물에 흔들 흔들\n흘러 내려가는 그 상자를 보며\n눈을 감아도 보이는 아이와 \n눈을 맞추며\n주저 앉아 눈물을 흘렸겠지"
        },
        {
          "c_id": 5,
          "statement": "너의 삶의 참 주인 \n너의 참 부모이신\n하나님 그 손에 \n너의 삶을 맡긴다"
        },
        {
          "c_id": 6,
          "statement": "너의 삶의 참 주인 \n너를 이끄시는 주\n하나님 그 손에 \n너의 삶을 드린다"
        },
        {
          "c_id": 7,
          "statement": "그가 널 구원하시리 \n그가 널 이끄시리라\n그가 널 사용하시리 \n그가 너를 인도하시리"
        },
        {
          "c_id": 8,
          "statement": "너의 삶의 참 주인\n너의 삶의 참 주인 \n너의 참 부모이신\n하나님 그 손에 \n너의 삶을 맡긴다"
        },
        {
          "c_id": 9,
          "statement": "너의 삶의 참 주인 \n너를 이끄시는 주\n하나님 그 손에 \n너의 삶을 드린다"
        },
        {
          "c_id": 10,
          "statement": "너의 삶의 참 주인 \n너의 참 부모이신\n하나님 그 손에 \n너의 삶을 맡긴다"
        },
        {
          "c_id": 11,
          "statement": "너의 삶의 참 주인 \n너를 이끄시는 주\n하나님 그 손에 \n너의 삶을 드린다"
        },
        {
          "c_id": 12,
          "statement": "어떤 맘이었을까 \n그녀의 두 눈엔\n눈물이 흐르고 흘러"
        }
      ],
      "file": "요게뱃의 노래.jpg",
      "title": "요게뱃의 노래",
      "code": "D",
      "l_id": 2
    },
    {
      "contents": [
        {
          "c_id": 0,
          "statement": "오직 예수 다른 이름은 없네 \n주 이름만 우리에게 주셨네 "
        },
        {
          "c_id": 1,
          "statement": "오직 예수 다른 이름 없네 \n오 영광과 존귀 권세와 찬양 받으실 분 \n오직 주 예수"
        },
        {
          "c_id": 2,
          "statement": "온 땅 위에 홀로 높으신 이름\n하늘 위 높이 들리셨네 온 땅 위에 홀로 높으신 이름 \n영광과 존귀와 찬양 드리세"
        }
      ],
      "title": "오직 예수 다른 이름은 없네",
      "file": "오직예수다른이름은없네D.jpg",
      "code": "D",
      "l_id": 3
    }
  ]
}